skote/__init__.py
skote/cli/generate_cli.py
skote/compat/backends.py
skote/distributed/collectives.py
skote/distributed/devicemgr.py
skote/distributed/kv_store.py
skote/distributed/launcher.py
skote/distributed/router.py
skote/distributed/speculative.py
skote/eval/runner.py
skote/eval/scenarios.py
skote/graph/capture_decode.py
skote/kernels/triton_ops.py
skote/runtime/decode_graph_adapter.py
skote/runtime/generate.py
skote/runtime/graphmgr.py
skote/runtime/metrics.py
skote/runtime/pkv.py
skote/runtime/router.py
skote/runtime/scheduler.py
skote/runtime/sgmv.py
skote/runtime/upm.py
skotergy-1.0.1.dist-info/licenses/LICENSE
skotergy-1.0.1.dist-info/METADATA
skotergy-1.0.1.dist-info/WHEEL
skotergy-1.0.1.dist-info/entry_points.txt
skotergy-1.0.1.dist-info/top_level.txt
skotergy-1.0.1.dist-info/RECORD
