Metadata-Version: 2.4
Name: skotergy
Version: 1.0.1
Summary: Skotergy: latency-first LLM inference with single-GPU closure and request-level multi-GPU routing.
Author: Skotergy Authors
License-Expression: Apache-2.0
Project-URL: Homepage, https://github.com/brucewang123456789/Private-Vault/tree/skotergy
Project-URL: Source, https://github.com/brucewang123456789/Private-Vault
Project-URL: Issues, https://github.com/brucewang123456789/Private-Vault/issues
Project-URL: Documentation, https://github.com/brucewang123456789/Private-Vault/tree/skotergy#readme
Keywords: llm,inference,router,triton,cuda,mps,xpu
Classifier: Programming Language :: Python
Classifier: Programming Language :: Python :: 3
Classifier: Programming Language :: Python :: 3 :: Only
Classifier: Programming Language :: Python :: 3.9
Classifier: Programming Language :: Python :: 3.10
Classifier: Programming Language :: Python :: 3.11
Classifier: Programming Language :: Python :: 3.12
Classifier: Programming Language :: Python :: 3.13
Classifier: Operating System :: OS Independent
Classifier: Intended Audience :: Developers
Classifier: Intended Audience :: Science/Research
Classifier: Topic :: Scientific/Engineering :: Artificial Intelligence
Classifier: Topic :: Software Development :: Libraries
Requires-Python: >=3.9
License-File: LICENSE
Requires-Dist: transformers<5,>=4.42
Requires-Dist: sentencepiece>=0.1.99
Requires-Dist: filelock>=3.12
Requires-Dist: packaging>=23
Provides-Extra: serve
Requires-Dist: fastapi>=0.110; extra == "serve"
Requires-Dist: uvicorn[standard]>=0.29; extra == "serve"
Provides-Extra: dev
Requires-Dist: pytest>=8; extra == "dev"
Requires-Dist: ruff>=0.5; extra == "dev"
Requires-Dist: mypy>=1.8; extra == "dev"
Requires-Dist: build>=1.2; extra == "dev"
Requires-Dist: twine>=5; extra == "dev"
Provides-Extra: accel
Requires-Dist: accelerate>=0.31; extra == "accel"
Dynamic: license-file
